setup.py
zdup.py
zdup.egg-info/PKG-INFO
zdup.egg-info/SOURCES.txt
zdup.egg-info/dependency_links.txt
zdup.egg-info/entry_points.txt
zdup.egg-info/not-zip-safe
zdup.egg-info/top_level.txt