Metadata-Version: 1.1
Name: zdup
Version: 1.1
Summary: Z Duplicity
Home-page: https://github.com/dstufft/zdup
Author: Donald Stufft
Author-email: donald@stufft.io
License: Apache License v2.0
Platform: UNKNOWN
Classifier: License :: OSI Approved :: Apache Software License
Classifier: Programming Language :: Python
Classifier: Programming Language :: Python :: 2
Classifier: Programming Language :: Python :: 2.7
Classifier: Programming Language :: Python :: Implementation :: CPython
Classifier: Programming Language :: Python :: Implementation :: PyPy
